LICENSE
bodhiext/common/__init__.py
bodhiext/common/_version.py
bodhiext/data_loader/__init__.py
bodhiext/data_loader/_file.py
bodhiext/data_loader/_plugin.py
bodhiext/prompt_source/__init__.py
bodhiext/prompt_source/_prompt_source.py
bodhiext/prompt_source/_yaml.py
bodhiext/prompt_source/templates/__init__.py
bodhiext/prompt_source/templates/default_prompt_templates.yaml
bodhiext/prompt_template/__init__.py
bodhiext/prompt_template/_string_prompt_template.py
bodhiext/splitter/__init__.py
bodhiext/splitter/_plugin.py
bodhiext/splitter/_text_splitter.py
bodhiext_common-0.2.1.dist-info/LICENSE
bodhiext_common-0.2.1.dist-info/METADATA
bodhiext_common-0.2.1.dist-info/WHEEL
bodhiext_common-0.2.1.dist-info/entry_points.txt
bodhiext_common-0.2.1.dist-info/RECORD
