Metadata-Version: 2.1
Name: bodhiext.common
Version: 0.2.1
Summary: A collection of independent common plugins for bodhilib
License: MIT
Author: Amir Nagri
Author-email: amir.nagri@proton.me
Requires-Python: >=3.8.1,<3.12
Classifier: License :: OSI Approved :: MIT License
Classifier: Programming Language :: Python :: 3
Classifier: Programming Language :: Python :: 3.9
Classifier: Programming Language :: Python :: 3.10
Classifier: Programming Language :: Python :: 3.11
Requires-Dist: bodhilib (>=0.1.12)
